kyss/__about__.py
kyss/__init__.py
kyss/ast.py
kyss/errors.py
kyss/recursive_descent.py
kyss/schema.py
kyss/schema_file.py
kyss/tool.py
kyss/typed_schema.py
kyss-1.0.0.dist-info/METADATA
kyss-1.0.0.dist-info/WHEEL
kyss-1.0.0.dist-info/licenses/LICENSE
kyss-1.0.0.dist-info/RECORD
