Metadata-Version: 2.1
Name: kyss
Version: 1.0.0
Summary: A YAML-inspired configuration language that keeps it simple
Project-URL: Documentation, https://github.com/gvx/kyss#readme
Project-URL: Issues, https://github.com/gvx/kyss/issues
Project-URL: Source, https://github.com/gvx/kyss
Author-email: "R.E.J. Wellner" <gyvox.public@gmail.com>
License-Expression: MIT
License-File: LICENSE
Keywords: configuration
Classifier: Development Status :: 4 - Beta
Classifier: Programming Language :: Python
Classifier: Programming Language :: Python :: 3.12
Classifier: Programming Language :: Python :: Implementation :: CPython
Classifier: Programming Language :: Python :: Implementation :: PyPy
Requires-Python: >=3.12
